restalker/LICENSE
restalker/__init__.py
restalker/link_extractors.py
restalker/metadata.py
restalker/restalker.py
restalker/textan.py
restalker-2.1.0.dist-info/LICENSE
restalker-2.1.0.dist-info/METADATA
restalker-2.1.0.dist-info/WHEEL
restalker-2.1.0.dist-info/RECORD
