Metadata-Version: 2.1
Name: restalker
Version: 2.1.0
Summary: Text analyzer package
License: MIT
Author: Javier Junquera-Sánchez
Author-email: javier@junquera.io
Requires-Python: >=3.10,<4.0
Classifier: License :: OSI Approved :: MIT License
Classifier: Programming Language :: Python :: 3
Classifier: Programming Language :: Python :: 3.10
Classifier: Programming Language :: Python :: 3.11
Classifier: Programming Language :: Python :: 3.12
Requires-Dist: based58
Requires-Dist: bech32ref
Requires-Dist: bip-utils
Requires-Dist: bs4 (>=0.0.2,<0.0.3)
Requires-Dist: gliner
Requires-Dist: lxml
Requires-Dist: monero
Requires-Dist: numpy
Requires-Dist: phonenumbers
Requires-Dist: web3
